{
    "data": {
        "count": 3,
        "items": [
            {
                "photo": "https://cdn0.iconfinder.com/data/icons/small-n-flat/24/678109-profile-group-128.png",
                "content": "Shubham posted a photo on your wall",
                "link" : "http://www.google.com"
            },
            {
                "photo": "https://cdn0.iconfinder.com/data/icons/small-n-flat/24/678109-profile-group-128.png",
                "content": "Shubham posted a photo on your wall",
                "link" : "http://www.google.com"
            },
            {
                "photo": "https://cdn0.iconfinder.com/data/icons/small-n-flat/24/678109-profile-group-128.png",
                "content": "Shubham posted a photo on your wall",
                "link" : "http://www.google.com"
            }
        ]
    }
}